FiinQuant/Aggregates.py
FiinQuant/Aggregates.pyi
FiinQuant/CoveredWarrantData.py
FiinQuant/CoveredWarrantData.pyi
FiinQuant/DerivativeData.py
FiinQuant/DerivativeData.pyi
FiinQuant/FiinIndicator.py
FiinQuant/FiinIndicator.pyi
FiinQuant/FiinSession.py
FiinQuant/FiinSession.pyi
FiinQuant/IndexData.py
FiinQuant/IndexData.pyi
FiinQuant/SubscribeCoveredWarrantEvents.py
FiinQuant/SubscribeCoveredWarrantEvents.pyi
FiinQuant/SubscribeDerivativeEvents.py
FiinQuant/SubscribeDerivativeEvents.pyi
FiinQuant/SubscribeIndexEvents.py
FiinQuant/SubscribeIndexEvents.pyi
FiinQuant/SubscribeTickerEvents.py
FiinQuant/SubscribeTickerEvents.pyi
FiinQuant/SubscribeTickerUpdate.py
FiinQuant/SubscribeTickerUpdate.pyi
FiinQuant/TickerData.py
FiinQuant/TickerData.pyi
FiinQuant/__init__.py
testfq-0.0.0.5.dist-info/METADATA
testfq-0.0.0.5.dist-info/WHEEL
testfq-0.0.0.5.dist-info/top_level.txt
testfq-0.0.0.5.dist-info/RECORD
